// class version 50.0 (50)
// access flags 33
public class Simple {

  // compiled from: Simple.asm

  // access flags 1
  public <init>()V
   L0
    LINENUMBER 8 L0
    NEW incubator/jvmsimu/JVMThread
    DUP
    NEW incubator/jvmsimu/JVM
    DUP
    INVOKESPECIAL incubator/jvmsimu/JVM.<init> ()V
    NEW incubator/jvmsimu/JVMStack
    DUP
    INVOKESPECIAL incubator/jvmsimu/JVMStack.<init> ()V
    INVOKESPECIAL incubator/jvmsimu/JVMThread.<init> (Lincubator/jvmsimu/JVM;Lincubator/jvmsimu/JVMStack;)V
    ASTORE 3
    ALOAD 0
    INVOKESPECIAL java/lang/Object.<init> ()V
    LDC 13
    ISTORE 1
    LDC "RETURN"
    ASTORE 2
   L1
    LINENUMBER 13 L1
    ALOAD 3
    NEW org/objectweb/asm/tree/InsnNode
    DUP
    LDC 177
    INVOKESPECIAL org/objectweb/asm/tree/InsnNode.<init> (I)V
    ACONST_NULL
    INVOKEVIRTUAL incubator/jvmsimu/JVMThread.process (Lorg/objectweb/asm/tree/AbstractInsnNode;[Ljava/lang/Object;)[Ljava/lang/Object;
    POP
    RETURN
   L2
    LOCALVARIABLE this LSimple; L0 L2 0
    LOCALVARIABLE lineNumber I L0 L2 1
    LOCALVARIABLE $_content_$ Ljava/lang/String; L0 L2 2
    LOCALVARIABLE $_context_$ Lincubator/jvmsimu/JVMThread; L0 L2 3
    MAXSTACK = 11
    MAXLOCALS = 4

  // access flags 9
  public static get()I
   L0
    LINENUMBER 20 L0
   FRAME FULL [] []
    NEW incubator/jvmsimu/JVMThread
    DUP
    NEW incubator/jvmsimu/JVM
    DUP
    INVOKESPECIAL incubator/jvmsimu/JVM.<init> ()V
    NEW incubator/jvmsimu/JVMStack
    DUP
    INVOKESPECIAL incubator/jvmsimu/JVMStack.<init> ()V
    INVOKESPECIAL incubator/jvmsimu/JVMThread.<init> (Lincubator/jvmsimu/JVM;Lincubator/jvmsimu/JVMStack;)V
    ASTORE 2
    LDC 24
    ISTORE 0
    LDC "ICONST_1"
    ASTORE 1
   L1
    LINENUMBER 24 L1
    ALOAD 2
    NEW org/objectweb/asm/tree/InsnNode
    DUP
    LDC 4
    INVOKESPECIAL org/objectweb/asm/tree/InsnNode.<init> (I)V
    ACONST_NULL
    INVOKEVIRTUAL incubator/jvmsimu/JVMThread.process (Lorg/objectweb/asm/tree/AbstractInsnNode;[Ljava/lang/Object;)[Ljava/lang/Object;
    POP
    LDC 25
    ISTORE 0
    LDC "ISTORE"
    ASTORE 1
   L2
    LINENUMBER 25 L2
    ALOAD 2
    NEW org/objectweb/asm/tree/VarInsnNode
    DUP
    LDC 54
    LDC 3
    INVOKESPECIAL org/objectweb/asm/tree/VarInsnNode.<init> (II)V
    ACONST_NULL
    INVOKEVIRTUAL incubator/jvmsimu/JVMThread.process (Lorg/objectweb/asm/tree/AbstractInsnNode;[Ljava/lang/Object;)[Ljava/lang/Object;
    ICONST_0
    AALOAD
    CHECKCAST java/lang/Integer
    INVOKEVIRTUAL java/lang/Integer.intValue ()I
    ISTORE 3
    LDC 28
    ISTORE 0
    LDC "ICONST_0"
    ASTORE 1
   L3
    LINENUMBER 28 L3
    ALOAD 2
    NEW org/objectweb/asm/tree/InsnNode
    DUP
    LDC 3
    INVOKESPECIAL org/objectweb/asm/tree/InsnNode.<init> (I)V
    ACONST_NULL
    INVOKEVIRTUAL incubator/jvmsimu/JVMThread.process (Lorg/objectweb/asm/tree/AbstractInsnNode;[Ljava/lang/Object;)[Ljava/lang/Object;
    POP
    LDC 29
    ISTORE 0
    LDC "ISTORE"
    ASTORE 1
   L4
    LINENUMBER 29 L4
    ALOAD 2
    NEW org/objectweb/asm/tree/VarInsnNode
    DUP
    LDC 54
    LDC 4
    INVOKESPECIAL org/objectweb/asm/tree/VarInsnNode.<init> (II)V
    ACONST_NULL
    INVOKEVIRTUAL incubator/jvmsimu/JVMThread.process (Lorg/objectweb/asm/tree/AbstractInsnNode;[Ljava/lang/Object;)[Ljava/lang/Object;
    ICONST_0
    AALOAD
    CHECKCAST java/lang/Integer
    INVOKEVIRTUAL java/lang/Integer.intValue ()I
    ISTORE 4
    LDC 31
    ISTORE 0
    LDC "GOTO"
    ASTORE 1
   L5
    LINENUMBER 31 L5
    ALOAD 2
    NEW org/objectweb/asm/tree/JumpInsnNode
    DUP
    LDC 167
    ACONST_NULL
    INVOKESPECIAL org/objectweb/asm/tree/JumpInsnNode.<init> (ILorg/objectweb/asm/tree/LabelNode;)V
    ACONST_NULL
    INVOKEVIRTUAL incubator/jvmsimu/JVMThread.process (Lorg/objectweb/asm/tree/AbstractInsnNode;[Ljava/lang/Object;)[Ljava/lang/Object;
    POP
    GOTO L6
   L7
   FRAME FULL [I I] []
    LDC 35
    ISTORE 0
    LDC "ILOAD"
    ASTORE 1
   L8
    LINENUMBER 35 L8
    ALOAD 2
    NEW org/objectweb/asm/tree/VarInsnNode
    DUP
    LDC 21
    LDC 3
    INVOKESPECIAL org/objectweb/asm/tree/VarInsnNode.<init> (II)V
    ICONST_1
    ANEWARRAY java/lang/Object
    DUP
    ICONST_0
    ILOAD 3
    INVOKESTATIC java/lang/Integer.valueOf (I)Ljava/lang/Integer;
    AASTORE
    INVOKEVIRTUAL incubator/jvmsimu/JVMThread.process (Lorg/objectweb/asm/tree/AbstractInsnNode;[Ljava/lang/Object;)[Ljava/lang/Object;
    POP
    LDC 36
    ISTORE 0
    LDC "ILOAD"
    ASTORE 1
   L9
    LINENUMBER 36 L9
    ALOAD 2
    NEW org/objectweb/asm/tree/VarInsnNode
    DUP
    LDC 21
    LDC 3
    INVOKESPECIAL org/objectweb/asm/tree/VarInsnNode.<init> (II)V
    ICONST_1
    ANEWARRAY java/lang/Object
    DUP
    ICONST_0
    ILOAD 3
    INVOKESTATIC java/lang/Integer.valueOf (I)Ljava/lang/Integer;
    AASTORE
    INVOKEVIRTUAL incubator/jvmsimu/JVMThread.process (Lorg/objectweb/asm/tree/AbstractInsnNode;[Ljava/lang/Object;)[Ljava/lang/Object;
    POP
    LDC 37
    ISTORE 0
    LDC "IADD"
    ASTORE 1
   L10
    LINENUMBER 37 L10
    ALOAD 2
    NEW org/objectweb/asm/tree/InsnNode
    DUP
    LDC 96
    INVOKESPECIAL org/objectweb/asm/tree/InsnNode.<init> (I)V
    ACONST_NULL
    INVOKEVIRTUAL incubator/jvmsimu/JVMThread.process (Lorg/objectweb/asm/tree/AbstractInsnNode;[Ljava/lang/Object;)[Ljava/lang/Object;
    POP
    LDC 38
    ISTORE 0
    LDC "ISTORE"
    ASTORE 1
   L11
    LINENUMBER 38 L11
    ALOAD 2
    NEW org/objectweb/asm/tree/VarInsnNode
    DUP
    LDC 54
    LDC 3
    INVOKESPECIAL org/objectweb/asm/tree/VarInsnNode.<init> (II)V
    ACONST_NULL
    INVOKEVIRTUAL incubator/jvmsimu/JVMThread.process (Lorg/objectweb/asm/tree/AbstractInsnNode;[Ljava/lang/Object;)[Ljava/lang/Object;
    ICONST_0
    AALOAD
    CHECKCAST java/lang/Integer
    INVOKEVIRTUAL java/lang/Integer.intValue ()I
    ISTORE 3
    LDC 41
    ISTORE 0
    LDC "IINC 1"
    ASTORE 1
   L12
    LINENUMBER 41 L12
    ALOAD 2
    NEW org/objectweb/asm/tree/IincInsnNode
    DUP
    LDC 4
    LDC 1
    INVOKESPECIAL org/objectweb/asm/tree/IincInsnNode.<init> (II)V
    ICONST_1
    ANEWARRAY java/lang/Object
    DUP
    ICONST_0
    ILOAD 4
    INVOKESTATIC java/lang/Integer.valueOf (I)Ljava/lang/Integer;
    AASTORE
    INVOKEVIRTUAL incubator/jvmsimu/JVMThread.process (Lorg/objectweb/asm/tree/AbstractInsnNode;[Ljava/lang/Object;)[Ljava/lang/Object;
    ICONST_0
    AALOAD
    CHECKCAST java/lang/Integer
    INVOKEVIRTUAL java/lang/Integer.intValue ()I
    ISTORE 4
   L6
   FRAME FULL [I I] []
    LDC 44
    ISTORE 0
    LDC "ICONST_5"
    ASTORE 1
   L13
    LINENUMBER 44 L13
    ALOAD 2
    NEW org/objectweb/asm/tree/InsnNode
    DUP
    LDC 8
    INVOKESPECIAL org/objectweb/asm/tree/InsnNode.<init> (I)V
    ACONST_NULL
    INVOKEVIRTUAL incubator/jvmsimu/JVMThread.process (Lorg/objectweb/asm/tree/AbstractInsnNode;[Ljava/lang/Object;)[Ljava/lang/Object;
    POP
    LDC 45
    ISTORE 0
    LDC "ILOAD"
    ASTORE 1
   L14
    LINENUMBER 45 L14
    ALOAD 2
    NEW org/objectweb/asm/tree/VarInsnNode
    DUP
    LDC 21
    LDC 4
    INVOKESPECIAL org/objectweb/asm/tree/VarInsnNode.<init> (II)V
    ICONST_1
    ANEWARRAY java/lang/Object
    DUP
    ICONST_0
    ILOAD 4
    INVOKESTATIC java/lang/Integer.valueOf (I)Ljava/lang/Integer;
    AASTORE
    INVOKEVIRTUAL incubator/jvmsimu/JVMThread.process (Lorg/objectweb/asm/tree/AbstractInsnNode;[Ljava/lang/Object;)[Ljava/lang/Object;
    POP
    LDC 46
    ISTORE 0
    LDC "IF_ICMPGE"
    ASTORE 1
   L15
    LINENUMBER 46 L15
    ALOAD 2
    NEW org/objectweb/asm/tree/JumpInsnNode
    DUP
    LDC 162
    ACONST_NULL
    INVOKESPECIAL org/objectweb/asm/tree/JumpInsnNode.<init> (ILorg/objectweb/asm/tree/LabelNode;)V
    ACONST_NULL
    INVOKEVIRTUAL incubator/jvmsimu/JVMThread.process (Lorg/objectweb/asm/tree/AbstractInsnNode;[Ljava/lang/Object;)[Ljava/lang/Object;
    DUP
    ICONST_0
    AALOAD
    CHECKCAST java/lang/Integer
    INVOKEVIRTUAL java/lang/Integer.intValue ()I
    SWAP
    ICONST_1
    AALOAD
    CHECKCAST java/lang/Integer
    INVOKEVIRTUAL java/lang/Integer.intValue ()I
    IF_ICMPGE L8
    LDC 49
    ISTORE 0
    LDC "ILOAD"
    ASTORE 1
   L16
    LINENUMBER 49 L16
    ALOAD 2
    NEW org/objectweb/asm/tree/VarInsnNode
    DUP
    LDC 21
    LDC 3
    INVOKESPECIAL org/objectweb/asm/tree/VarInsnNode.<init> (II)V
    ICONST_1
    ANEWARRAY java/lang/Object
    DUP
    ICONST_0
    ILOAD 3
    INVOKESTATIC java/lang/Integer.valueOf (I)Ljava/lang/Integer;
    AASTORE
    INVOKEVIRTUAL incubator/jvmsimu/JVMThread.process (Lorg/objectweb/asm/tree/AbstractInsnNode;[Ljava/lang/Object;)[Ljava/lang/Object;
    POP
    LDC 50
    ISTORE 0
    LDC "INVOKESTATIC"
    ASTORE 1
   L17
    LINENUMBER 50 L17
    ALOAD 2
    NEW org/objectweb/asm/tree/MethodInsnNode
    DUP
    LDC 184
    LDC "Simple"
    LDC "get"
    LDC "(I)I"
    INVOKESPECIAL org/objectweb/asm/tree/MethodInsnNode.<init> (ILjava/lang/String;Ljava/lang/String;Ljava/lang/String;)V
    ACONST_NULL
    INVOKEVIRTUAL incubator/jvmsimu/JVMThread.process (Lorg/objectweb/asm/tree/AbstractInsnNode;[Ljava/lang/Object;)[Ljava/lang/Object;
    ICONST_0
    AALOAD
    INVOKESTATIC Simple.get (I)I
    LDC 51
    ISTORE 0
    LDC "IRETURN"
    ASTORE 1
   L18
    LINENUMBER 51 L18
    ALOAD 2
    NEW org/objectweb/asm/tree/InsnNode
    DUP
    LDC 172
    INVOKESPECIAL org/objectweb/asm/tree/InsnNode.<init> (I)V
    ACONST_NULL
    INVOKEVIRTUAL incubator/jvmsimu/JVMThread.process (Lorg/objectweb/asm/tree/AbstractInsnNode;[Ljava/lang/Object;)[Ljava/lang/Object;
    ICONST_0
    AALOAD
    CHECKCAST java/lang/Integer
    INVOKEVIRTUAL java/lang/Integer.intValue ()I
    IRETURN
   L19
    LOCALVARIABLE lineNumber I L0 L19 0
    LOCALVARIABLE $_content_$ Ljava/lang/String; L0 L19 1
    LOCALVARIABLE $_context_$ Lincubator/jvmsimu/JVMThread; L0 L19 2
    LOCALVARIABLE temp I L0 L19 3
    LOCALVARIABLE i I L0 L19 4
    MAXSTACK = 12
    MAXLOCALS = 5

  // access flags 10
  private static get(I)I
   L0
    LINENUMBER 59 L0
    NEW incubator/jvmsimu/JVMThread
    DUP
    NEW incubator/jvmsimu/JVM
    DUP
    INVOKESPECIAL incubator/jvmsimu/JVM.<init> ()V
    NEW incubator/jvmsimu/JVMStack
    DUP
    INVOKESPECIAL incubator/jvmsimu/JVMStack.<init> ()V
    INVOKESPECIAL incubator/jvmsimu/JVMThread.<init> (Lincubator/jvmsimu/JVM;Lincubator/jvmsimu/JVMStack;)V
    ASTORE 2
    LDC 62
    ISTORE 0
    LDC "ILOAD"
    ASTORE 1
   L1
    LINENUMBER 62 L1
    ALOAD 2
    NEW org/objectweb/asm/tree/VarInsnNode
    DUP
    LDC 21
    LDC 3
    INVOKESPECIAL org/objectweb/asm/tree/VarInsnNode.<init> (II)V
    ICONST_1
    ANEWARRAY java/lang/Object
    DUP
    ICONST_0
    ILOAD 3
    INVOKESTATIC java/lang/Integer.valueOf (I)Ljava/lang/Integer;
    AASTORE
    INVOKEVIRTUAL incubator/jvmsimu/JVMThread.process (Lorg/objectweb/asm/tree/AbstractInsnNode;[Ljava/lang/Object;)[Ljava/lang/Object;
    POP
    LDC 63
    ISTORE 0
    LDC "ICONST_M1"
    ASTORE 1
   L2
    LINENUMBER 63 L2
    ALOAD 2
    NEW org/objectweb/asm/tree/InsnNode
    DUP
    LDC 2
    INVOKESPECIAL org/objectweb/asm/tree/InsnNode.<init> (I)V
    ACONST_NULL
    INVOKEVIRTUAL incubator/jvmsimu/JVMThread.process (Lorg/objectweb/asm/tree/AbstractInsnNode;[Ljava/lang/Object;)[Ljava/lang/Object;
    POP
    LDC 64
    ISTORE 0
    LDC "IADD"
    ASTORE 1
   L3
    LINENUMBER 64 L3
    ALOAD 2
    NEW org/objectweb/asm/tree/InsnNode
    DUP
    LDC 96
    INVOKESPECIAL org/objectweb/asm/tree/InsnNode.<init> (I)V
    ACONST_NULL
    INVOKEVIRTUAL incubator/jvmsimu/JVMThread.process (Lorg/objectweb/asm/tree/AbstractInsnNode;[Ljava/lang/Object;)[Ljava/lang/Object;
    POP
    LDC 65
    ISTORE 0
    LDC "IRETURN"
    ASTORE 1
   L4
    LINENUMBER 65 L4
    ALOAD 2
    NEW org/objectweb/asm/tree/InsnNode
    DUP
    LDC 172
    INVOKESPECIAL org/objectweb/asm/tree/InsnNode.<init> (I)V
    ACONST_NULL
    INVOKEVIRTUAL incubator/jvmsimu/JVMThread.process (Lorg/objectweb/asm/tree/AbstractInsnNode;[Ljava/lang/Object;)[Ljava/lang/Object;
    ICONST_0
    AALOAD
    CHECKCAST java/lang/Integer
    INVOKEVIRTUAL java/lang/Integer.intValue ()I
    IRETURN
   L5
    LOCALVARIABLE lineNumber I L0 L5 0
    LOCALVARIABLE $_content_$ Ljava/lang/String; L0 L5 1
    LOCALVARIABLE $_context_$ Lincubator/jvmsimu/JVMThread; L0 L5 2
    LOCALVARIABLE temp I L0 L5 3
    MAXSTACK = 12
    MAXLOCALS = 4
}
